Firo/FiroDB.py
Firo/__init__.py
Firo-1.2.0.dist-info/METADATA
Firo-1.2.0.dist-info/WHEEL
Firo-1.2.0.dist-info/top_level.txt
Firo-1.2.0.dist-info/RECORD
