Metadata-Version: 2.1
Name: Firo
Version: 1.2.0
Summary: A Realtime, No SQL Database
Home-page: https://github.com/circutrider21/FiroDB
Author: Peeled Fruit Studios
Author-email: Circutrider21@gmail.com
License: UNKNOWN
Platform: UNKNOWN
Classifier: Intended Audience :: Developers
Classifier: License :: OSI Approved :: MIT License
Classifier: Topic :: Database
Requires-Python: >=3.6
